mushu/__init__.py
mushu/helpers.py
mushu/py.typed
mushu/wrappers.py
mushu/auth/__init__.py
mushu/auth/client.py
mushu/auth/errors.py
mushu/auth/types.py
mushu/auth/api/__init__.py
mushu/auth/api/auth/__init__.py
mushu/auth/api/auth/apple_authorize.py
mushu/auth/api/auth/apple_callback.py
mushu/auth/api/auth/apple_s2s_notifications.py
mushu/auth/api/auth/google_authorize.py
mushu/auth/api/auth/google_callback.py
mushu/auth/api/auth/google_risc_notifications.py
mushu/auth/api/auth/logout.py
mushu/auth/api/auth/refresh_session.py
mushu/auth/api/auth/sign_in_with_apple.py
mushu/auth/api/auth/sign_in_with_google.py
mushu/auth/api/auth/validate_token.py
mushu/auth/api/auth_providers/__init__.py
mushu/auth/api/auth_providers/create_auth_provider.py
mushu/auth/api/auth_providers/delete_auth_provider.py
mushu/auth/api/auth_providers/get_auth_provider.py
mushu/auth/api/auth_providers/list_auth_providers.py
mushu/auth/api/auth_providers/update_auth_provider.py
mushu/auth/api/health/__init__.py
mushu/auth/api/health/health_check_health_get.py
mushu/auth/api/health/root_get.py
mushu/auth/api/users/__init__.py
mushu/auth/api/users/get_current_user.py
mushu/auth/models/__init__.py
mushu/auth/models/apple_s2s_notifications_response_apple_s2s_notifications.py
mushu/auth/models/apple_s2s_request.py
mushu/auth/models/apple_sign_in_request.py
mushu/auth/models/auth_provider.py
mushu/auth/models/auth_provider_list_response.py
mushu/auth/models/auth_provider_type.py
mushu/auth/models/body_apple_callback.py
mushu/auth/models/create_auth_provider_request.py
mushu/auth/models/delete_auth_provider_response_delete_auth_provider.py
mushu/auth/models/google_risc_notifications_response_google_risc_notifications.py
mushu/auth/models/google_risc_request.py
mushu/auth/models/google_sign_in_request.py
mushu/auth/models/health_response.py
mushu/auth/models/http_validation_error.py
mushu/auth/models/logout_response_logout.py
mushu/auth/models/refresh_token_request.py
mushu_sdk-0.2.2.dist-info/METADATA
mushu_sdk-0.2.2.dist-info/WHEEL
mushu_sdk-0.2.2.dist-info/RECORD
