Metadata-Version: 2.4
Name: mushu-sdk
Version: 0.2.2
Summary: Python SDK for Mushu API - auto-generated clients from OpenAPI specs
Project-URL: Homepage, https://admin.mushucorp.com
Project-URL: Documentation, https://admin.mushucorp.com/docs
Project-URL: Repository, https://github.com/mushucorp/mushu
License: MIT
Keywords: api,mushu,openapi,sdk
Requires-Python: >=3.11
Requires-Dist: attrs>=23.0.0
Requires-Dist: httpx>=0.25.0
